get_my_fonts/LICENSE
get_my_fonts/README.MD
get_my_fonts/__init__.py
get_my_fonts/requirements.txt
get_my_fonts/thirdparty.json
get_my_fonts-0.10.dist-info/LICENSE.rst
get_my_fonts-0.10.dist-info/METADATA
get_my_fonts-0.10.dist-info/WHEEL
get_my_fonts-0.10.dist-info/top_level.txt
get_my_fonts-0.10.dist-info/RECORD
